{
  "key_insight": "The integration of machine learning with domain-specific physics is transforming the design, monitoring, and control of electricity systems, where data scarcity, limited interpretability, and the need to enforce physical laws constrain purely data-driven model",
  "engineering_relevance": "Potential relevance: fem surrogates workflows and research evaluation.",
  "method": [
    "AI Solid Mechanics paper selected from recent arXiv submissions.",
    "Ranked by recency plus AI and solid mechanics relevance signals.",
    "Use the linked paper for methods, data, and validation details."
  ],
  "evidence_signal": "Evidence details are summarized from the public abstract only.",
  "watch_item": "Review the full paper for assumptions, validation data, mesh or material scope, and generalization limits.",
  "hashtags": [
    "#AISolidMechanics",
    "#ComputationalMechanics",
    "#ScientificML",
    "#MaterialsAI",
    "#arXiv"
  ],
  "paper_id": "2026-05-21-arxiv-engineering_hybrid_physics_informed_neural_networks_for_next_generation_electricity_system",
  "paper_title": "Engineering Hybrid Physics-Informed Neural Networks for Next-Generation Electricity Systems: A State-of-the-Art Review",
  "paper_date": "2026-05-21",
  "paper_category": "FEM Surrogates",
  "generated_at": "2026-05-30T10:59:10",
  "generator": "fallback"
}